restructured/__init__.py
restructured/_generated/.openapi-generator/FILES
restructured/_generated/.openapi-generator/VERSION
restructured/_generated/.openapi-generator-ignore
restructured/_generated/__init__.py
restructured/_generated/openapi_client/__init__.py
restructured/_generated/openapi_client/api/__init__.py
restructured/_generated/openapi_client/api/client_api.py
restructured/_generated/openapi_client/api_client.py
restructured/_generated/openapi_client/api_response.py
restructured/_generated/openapi_client/configuration.py
restructured/_generated/openapi_client/exceptions.py
restructured/_generated/openapi_client/models/__init__.py
restructured/_generated/openapi_client/models/agent_run.py
restructured/_generated/openapi_client/models/agent_run_result.py
restructured/_generated/openapi_client/models/agent_run_result_metadata.py
restructured/_generated/openapi_client/models/agent_run_result_metadata_citation.py
restructured/_generated/openapi_client/models/cell_result_user_data.py
restructured/_generated/openapi_client/models/cell_result_user_input.py
restructured/_generated/openapi_client/models/http_validation_error.py
restructured/_generated/openapi_client/models/list_agent_runs_response.py
restructured/_generated/openapi_client/models/validation_error.py
restructured/_generated/openapi_client/models/validation_error_loc_inner.py
restructured/_generated/openapi_client/models/value.py
restructured/_generated/openapi_client/models/value_any_of_inner_value.py
restructured/_generated/openapi_client/rest.py
restructured/_generated/openapi_client_README.md
restructured/_resources/agent_run.py
restructured/_utils/client.py
restructured/_utils/config.py
restructured/_utils/webhook.py
restructured/cli.py
restructured/types/__init__.py
restructured/types/agent_run.py
restructured-0.2.3.dist-info/LICENSE
restructured-0.2.3.dist-info/METADATA
restructured-0.2.3.dist-info/WHEEL
restructured-0.2.3.dist-info/entry_points.txt
restructured-0.2.3.dist-info/RECORD
